dynamic_dt/__init__.py
dynamic_dt/wikipedia_data.txt
dynamic_datetime-0.1.27.dist-info/METADATA
dynamic_datetime-0.1.27.dist-info/WHEEL
dynamic_datetime-0.1.27.dist-info/licenses/LICENSE
dynamic_datetime-0.1.27.dist-info/RECORD
