Metadata-Version: 2.4
Name: Dynamic-DateTime
Version: 0.1.27
Summary: A versatile datetime class supporting extremely large timescales and extremely precise measurements.
Project-URL: Homepage, https://github.com/thomas-xin/Dynamic-DateTime
Project-URL: Repository, https://github.com/thomas-xin/Dynamic-DateTime
Project-URL: Issues, https://github.com/thomas-xin/Dynamic-DateTime/issues
Author-email: thomas-xin <thomasxin@gmail.com>
License-File: LICENSE
Classifier: License :: OSI Approved :: MIT License
Classifier: Operating System :: OS Independent
Classifier: Programming Language :: Python :: 3
Requires-Python: >=3.10
Requires-Dist: number-parser>=0.3.2
Requires-Dist: python-dateutil>=2.9.0
Requires-Dist: pytz>=2025.2
